pyexcel_xlsxw/__init__.py
pyexcel_xlsxw/xlsxw.py
pyexcel_xlsxw-0.6.1.dist-info/LICENSE
pyexcel_xlsxw-0.6.1.dist-info/METADATA
pyexcel_xlsxw-0.6.1.dist-info/WHEEL
pyexcel_xlsxw-0.6.1.dist-info/top_level.txt
pyexcel_xlsxw-0.6.1.dist-info/RECORD
