Metadata-Version: 1.2
Name: pyexcel-xlsxw
Version: 0.6.1
Summary: A wrapper library to write data in xlsx and xlsm format
Home-page: https://github.com/pyexcel/pyexcel-xlsxw
Author: chfw
Author-email: info@pyexcel.org
License: New BSD
Download-URL: https://github.com/pyexcel/pyexcel-xlsxw/archive/0.6.1.tar.gz
Keywords: python,xlsx
Platform: UNKNOWN
Classifier: Topic :: Software Development :: Libraries
Classifier: Programming Language :: Python
Classifier: Intended Audience :: Developers
Classifier: Programming Language :: Python :: 3 :: Only
Classifier: Programming Language :: Python :: 3.6
Classifier: Programming Language :: Python :: 3.7
Classifier: Programming Language :: Python :: 3.8
Classifier: Development Status :: 3 - Alpha
Classifier: Programming Language :: Python :: Implementation :: PyPy
Requires-Python: >=3.6
